{
    "bones": {
		"base": {"position": {"x": 0,"y": 0,"z": 0},"rotation": {"x": 0,"y": 0,"z": 0}}
	},
    "cached_mdl": {
		"onboard_console": {"path": "onboard_console.obj"},
		"speedo_textured": {"path": "speedo_textured.obj"}
	},
    "map_models": {
        "onboard_console": {
			"load": ["onboard_console:Kit3_Interior_Geo_lodA.048"],
			"texture": "interior",
			"bone": "base",
			"color": {"r": 255,"g": 255,"b": 255,"a": 255}
		},
        "speedo_textured": {
			"load": ["speedo_textured:Kit3_Interior_Geo_lodA.011"],
			"texture": "interior",
			"bone": "base",
			"color": {"r": 255,"g": 255,"b": 255,"a": 255}
		}
    }
}